MANIFEST.in
README.md
setup.py
mbglob/MbGlob.py
mbglob/__init__.py
mbglob.egg-info/PKG-INFO
mbglob.egg-info/SOURCES.txt
mbglob.egg-info/dependency_links.txt
mbglob.egg-info/not-zip-safe
mbglob.egg-info/top_level.txt