Metadata-Version: 1.0
Name: mbglob
Version: 0.0.3
Summary: mbglob is a wrapper libs for glob.glob.
Home-page: https://github.com/nabeen/mbglob
Author: nabeen
Author-email: watanabe_kenichiro@hasigo.co.jp
License: UNKNOWN
Platform: UNKNOWN
